soapcw/__init__.py
soapcw/cli.py
soapcw/soapcw.cpython-37m-darwin.so
soapcw/line_aware_stat/__init__.py
soapcw/line_aware_stat/gen_lookup_python.py
soapcw/line_aware_stat/save_lookup.py
soapcw/tools/__init__.py
soapcw/tools/plots.py
soapcw/tools/tools.py
tests/__init__.py
tests/test_soap.py
soapcw-0.1.2.dist-info/AUTHORS.rst
soapcw-0.1.2.dist-info/LICENSE
soapcw-0.1.2.dist-info/METADATA
soapcw-0.1.2.dist-info/WHEEL
soapcw-0.1.2.dist-info/entry_points.txt
soapcw-0.1.2.dist-info/top_level.txt
soapcw-0.1.2.dist-info/RECORD
