Metadata-Version: 2.1
Name: soapcw
Version: 0.1.2
Summary: SOAP is a rapid algorithm to search for continuous sources of gravitational waves, with a wider application to long duration narrowband signals.
Home-page: https://git.ligo.org/joseph.bayley/soapcw
Author: Joe Bayley
Author-email: j.bayley.1@research.gla.ac.uk
License: MIT license
Download-URL: https://git.ligo.org/joseph.bayley/soapcw/-/archive/0.1.2/soapcw-0.1.2.tar.gz
Keywords: soapcw,soap,gravitational waves,pulsars,neutron stars,continuous waves
Platform: UNKNOWN
Classifier: Development Status :: 2 - Pre-Alpha
Classifier: Intended Audience :: Developers
Classifier: License :: OSI Approved :: MIT License
Classifier: Natural Language :: English
Classifier: Programming Language :: Python :: 2
Classifier: Programming Language :: Python :: 2.7
Classifier: Programming Language :: Python :: 3
Classifier: Programming Language :: Python :: 3.4
Classifier: Programming Language :: Python :: 3.5
Classifier: Programming Language :: Python :: 3.6
Classifier: Programming Language :: Python :: 3.7
Requires-Dist: cython
